easyPB/__init__.py
easyPB/easypb.py
easyPB-0.0.4.dist-info/LICENSE
easyPB-0.0.4.dist-info/METADATA
easyPB-0.0.4.dist-info/WHEEL
easyPB-0.0.4.dist-info/top_level.txt
easyPB-0.0.4.dist-info/RECORD
