Metadata-Version: 2.1
Name: easyPB
Version: 0.0.4
Summary: 一个配置了进度条的文件拷贝，下载工具
Home-page: 
Author: newrain
Author-email: newrain <newrain_wang@163.com>
Project-URL: Homepage, https://gitee.com/newrain001/easy-pb
Project-URL: Bug Tracker, https://gitee.com/newrain001/easy-pb/issues
Classifier: Programming Language :: Python :: 3
Classifier: License :: OSI Approved :: MIT License
Classifier: Operating System :: OS Independent
Requires-Python: >=3.6.5
License-File: LICENSE
Requires-Dist: setuptools (>=61.0)
Requires-Dist: requests
Requires-Dist: tqdm
